{"data": [{"value": 13, "district": "TREA"}, {"value": 50, "district": "PORNOGRAPHY/OBSCENE MAT"}, {"value": 326, "district": "GAMBLING"}, {"value": 376, "district": "SEX OFFENSES, NON FORCIBLE"}, {"value": 669, "district": "EXTORTION"}, {"value": 732, "district": "BRIBERY"}, {"value": 891, "district": "BAD CHECKS"}, {"value": 1128, "district": "FAMILY OFFENSES"}, {"value": 1197, "district": "SUICIDE"}, {"value": 2382, "district": "LOITERING"}, {"value": 2748, "district": "EMBEZZLEMENT"}, {"value": 3524, "district": "ARSON"}, {"value": 3996, "district": "LIQUOR LAWS"}, {"value": 4113, "district": "RUNAWAY"}, {"value": 5076, "district": "KIDNAPPING"}, {"value": 5302, "district": "DRIVING UNDER THE INFLUENCE"}, {"value": 8052, "district": "RECOVERED VEHICLE"}, {"value": 9432, "district": "DRUNKENNESS"}, {"value": 9573, "district": "DISORDERLY CONDUCT"}, {"value": 10399, "district": "SEX OFFENSES, FORCIBLE"}, {"value": 10890, "district": "STOLEN PROPERTY"}, {"value": 16163, "district": "PROSTITUTION"}, {"value": 17468, "district": "TRESPASS"}, {"value": 20065, "district": "WEAPON LAWS"}, {"value": 22353, "district": "FORGERY/COUNTERFEITING"}, {"value": 23259, "district": "SECONDARY CODES"}, {"value": 38306, "district": "FRAUD"}, {"value": 51672, "district": "ROBBERY"}, {"value": 59458, "district": "MISSING PERSON"}, {"value": 72996, "district": "SUSPICIOUS OCC"}, {"value": 84017, "district": "BURGLARY"}, {"value": 94956, "district": "WARRANTS"}, {"value": 104251, "district": "VANDALISM"}, {"value": 115131, "district": "DRUG/NARCOTIC"}, {"value": 119824, "district": "VEHICLE THEFT"}, {"value": 177407, "district": "ASSAULT"}, {"value": 216773, "district": "NON-CRIMINAL"}, {"value": 286727, "district": "OTHER OFFENSES"}, {"value": 422170, "district": "LARCENY/THEFT"}]}